{
  "id": "ddde63f5-47aa-4b3e-b32b-4409f299091d",
  "prevId": "00000000-0000-0000-0000-000000000000",
  "version": "7",
  "dialect": "postgresql",
  "tables": {
    "designers.moodboard_comments": {
      "name": "moodboard_comments",
      "schema": "designers",
      "columns": {
        "id": {
          "name": "id",
          "type": "uuid",
          "primaryKey": true,
          "notNull": true,
          "default": "gen_random_uuid()"
        },
        "moodboard_id": {
          "name": "moodboard_id",
          "type": "uuid",
          "primaryKey": false,
          "notNull": true
        },
        "item_id": {
          "name": "item_id",
          "type": "uuid",
          "primaryKey": false,
          "notNull": false
        },
        "author_name": {
          "name": "author_name",
          "type": "text",
          "primaryKey": false,
          "notNull": true,
          "default": "'Anonymous'"
        },
        "content": {
          "name": "content",
          "type": "text",
          "primaryKey": false,
          "notNull": true
        },
        "slide_index": {
          "name": "slide_index",
          "type": "integer",
          "primaryKey": false,
          "notNull": false
        },
        "x": {
          "name": "x",
          "type": "double precision",
          "primaryKey": false,
          "notNull": false
        },
        "y": {
          "name": "y",
          "type": "double precision",
          "primaryKey": false,
          "notNull": false
        },
        "resolved": {
          "name": "resolved",
          "type": "boolean",
          "primaryKey": false,
          "notNull": false,
          "default": false
        },
        "created_at": {
          "name": "created_at",
          "type": "timestamp with time zone",
          "primaryKey": false,
          "notNull": false,
          "default": "now()"
        }
      },
      "indexes": {},
      "foreignKeys": {
        "moodboard_comments_moodboard_id_moodboards_id_fk": {
          "name": "moodboard_comments_moodboard_id_moodboards_id_fk",
          "tableFrom": "moodboard_comments",
          "tableTo": "moodboards",
          "schemaTo": "designers",
          "columnsFrom": [
            "moodboard_id"
          ],
          "columnsTo": [
            "id"
          ],
          "onDelete": "cascade",
          "onUpdate": "no action"
        }
      },
      "compositePrimaryKeys": {},
      "uniqueConstraints": {},
      "policies": {},
      "checkConstraints": {},
      "isRLSEnabled": false
    },
    "designers.moodboard_floorplan_zones": {
      "name": "moodboard_floorplan_zones",
      "schema": "designers",
      "columns": {
        "id": {
          "name": "id",
          "type": "uuid",
          "primaryKey": true,
          "notNull": true,
          "default": "gen_random_uuid()"
        },
        "item_id": {
          "name": "item_id",
          "type": "uuid",
          "primaryKey": false,
          "notNull": true
        },
        "name": {
          "name": "name",
          "type": "text",
          "primaryKey": false,
          "notNull": true
        },
        "color": {
          "name": "color",
          "type": "text",
          "primaryKey": false,
          "notNull": true
        },
        "points": {
          "name": "points",
          "type": "jsonb",
          "primaryKey": false,
          "notNull": true
        },
        "created_at": {
          "name": "created_at",
          "type": "timestamp with time zone",
          "primaryKey": false,
          "notNull": true,
          "default": "now()"
        }
      },
      "indexes": {},
      "foreignKeys": {
        "moodboard_floorplan_zones_item_id_moodboard_items_id_fk": {
          "name": "moodboard_floorplan_zones_item_id_moodboard_items_id_fk",
          "tableFrom": "moodboard_floorplan_zones",
          "tableTo": "moodboard_items",
          "schemaTo": "designers",
          "columnsFrom": [
            "item_id"
          ],
          "columnsTo": [
            "id"
          ],
          "onDelete": "cascade",
          "onUpdate": "no action"
        }
      },
      "compositePrimaryKeys": {},
      "uniqueConstraints": {},
      "policies": {},
      "checkConstraints": {},
      "isRLSEnabled": false
    },
    "designers.moodboard_items": {
      "name": "moodboard_items",
      "schema": "designers",
      "columns": {
        "id": {
          "name": "id",
          "type": "uuid",
          "primaryKey": true,
          "notNull": true,
          "default": "gen_random_uuid()"
        },
        "moodboard_id": {
          "name": "moodboard_id",
          "type": "uuid",
          "primaryKey": false,
          "notNull": true
        },
        "parent_frame_id": {
          "name": "parent_frame_id",
          "type": "uuid",
          "primaryKey": false,
          "notNull": false
        },
        "product_id": {
          "name": "product_id",
          "type": "uuid",
          "primaryKey": false,
          "notNull": false
        },
        "item_type": {
          "name": "item_type",
          "type": "text",
          "primaryKey": false,
          "notNull": false
        },
        "element_type": {
          "name": "element_type",
          "type": "text",
          "primaryKey": false,
          "notNull": false
        },
        "shape_type": {
          "name": "shape_type",
          "type": "text",
          "primaryKey": false,
          "notNull": false
        },
        "group_id": {
          "name": "group_id",
          "type": "uuid",
          "primaryKey": false,
          "notNull": false
        },
        "slide_index": {
          "name": "slide_index",
          "type": "integer",
          "primaryKey": false,
          "notNull": true,
          "default": 0
        },
        "z_index": {
          "name": "z_index",
          "type": "integer",
          "primaryKey": false,
          "notNull": false
        },
        "x": {
          "name": "x",
          "type": "double precision",
          "primaryKey": false,
          "notNull": true,
          "default": 0
        },
        "y": {
          "name": "y",
          "type": "double precision",
          "primaryKey": false,
          "notNull": true,
          "default": 0
        },
        "width": {
          "name": "width",
          "type": "double precision",
          "primaryKey": false,
          "notNull": true,
          "default": 200
        },
        "height": {
          "name": "height",
          "type": "double precision",
          "primaryKey": false,
          "notNull": true,
          "default": 200
        },
        "rotation": {
          "name": "rotation",
          "type": "double precision",
          "primaryKey": false,
          "notNull": false
        },
        "opacity": {
          "name": "opacity",
          "type": "double precision",
          "primaryKey": false,
          "notNull": false
        },
        "scale_x": {
          "name": "scale_x",
          "type": "double precision",
          "primaryKey": false,
          "notNull": false
        },
        "scale_y": {
          "name": "scale_y",
          "type": "double precision",
          "primaryKey": false,
          "notNull": false
        },
        "skew_x": {
          "name": "skew_x",
          "type": "double precision",
          "primaryKey": false,
          "notNull": false
        },
        "skew_y": {
          "name": "skew_y",
          "type": "double precision",
          "primaryKey": false,
          "notNull": false
        },
        "mirror_x": {
          "name": "mirror_x",
          "type": "boolean",
          "primaryKey": false,
          "notNull": false
        },
        "mirror_y": {
          "name": "mirror_y",
          "type": "boolean",
          "primaryKey": false,
          "notNull": false
        },
        "lock_ratio": {
          "name": "lock_ratio",
          "type": "boolean",
          "primaryKey": false,
          "notNull": false
        },
        "custom_image_url": {
          "name": "custom_image_url",
          "type": "text",
          "primaryKey": false,
          "notNull": false
        },
        "crop_data": {
          "name": "crop_data",
          "type": "jsonb",
          "primaryKey": false,
          "notNull": false
        },
        "filter": {
          "name": "filter",
          "type": "text",
          "primaryKey": false,
          "notNull": false
        },
        "feather": {
          "name": "feather",
          "type": "double precision",
          "primaryKey": false,
          "notNull": false
        },
        "fill_color": {
          "name": "fill_color",
          "type": "text",
          "primaryKey": false,
          "notNull": false
        },
        "fill_gradient": {
          "name": "fill_gradient",
          "type": "jsonb",
          "primaryKey": false,
          "notNull": false
        },
        "border_color": {
          "name": "border_color",
          "type": "text",
          "primaryKey": false,
          "notNull": false
        },
        "border_gradient": {
          "name": "border_gradient",
          "type": "jsonb",
          "primaryKey": false,
          "notNull": false
        },
        "border_position": {
          "name": "border_position",
          "type": "text",
          "primaryKey": false,
          "notNull": false
        },
        "border_radius": {
          "name": "border_radius",
          "type": "double precision",
          "primaryKey": false,
          "notNull": false
        },
        "border_width": {
          "name": "border_width",
          "type": "double precision",
          "primaryKey": false,
          "notNull": false
        },
        "shadow_enabled": {
          "name": "shadow_enabled",
          "type": "boolean",
          "primaryKey": false,
          "notNull": false
        },
        "shadow_color": {
          "name": "shadow_color",
          "type": "text",
          "primaryKey": false,
          "notNull": false
        },
        "shadow_blur": {
          "name": "shadow_blur",
          "type": "double precision",
          "primaryKey": false,
          "notNull": false
        },
        "shadow_x": {
          "name": "shadow_x",
          "type": "double precision",
          "primaryKey": false,
          "notNull": false
        },
        "shadow_y": {
          "name": "shadow_y",
          "type": "double precision",
          "primaryKey": false,
          "notNull": false
        },
        "text_content": {
          "name": "text_content",
          "type": "text",
          "primaryKey": false,
          "notNull": false
        },
        "text_style": {
          "name": "text_style",
          "type": "jsonb",
          "primaryKey": false,
          "notNull": false
        },
        "color_value": {
          "name": "color_value",
          "type": "text",
          "primaryKey": false,
          "notNull": false
        },
        "pin_corner": {
          "name": "pin_corner",
          "type": "text",
          "primaryKey": false,
          "notNull": false
        },
        "depth": {
          "name": "depth",
          "type": "double precision",
          "primaryKey": false,
          "notNull": false
        },
        "thickness": {
          "name": "thickness",
          "type": "double precision",
          "primaryKey": false,
          "notNull": false
        },
        "visible": {
          "name": "visible",
          "type": "boolean",
          "primaryKey": false,
          "notNull": false
        },
        "metadata": {
          "name": "metadata",
          "type": "jsonb",
          "primaryKey": false,
          "notNull": true,
          "default": "'{}'::jsonb"
        },
        "created_at": {
          "name": "created_at",
          "type": "timestamp with time zone",
          "primaryKey": false,
          "notNull": true,
          "default": "now()"
        }
      },
      "indexes": {},
      "foreignKeys": {
        "moodboard_items_moodboard_id_moodboards_id_fk": {
          "name": "moodboard_items_moodboard_id_moodboards_id_fk",
          "tableFrom": "moodboard_items",
          "tableTo": "moodboards",
          "schemaTo": "designers",
          "columnsFrom": [
            "moodboard_id"
          ],
          "columnsTo": [
            "id"
          ],
          "onDelete": "cascade",
          "onUpdate": "no action"
        }
      },
      "compositePrimaryKeys": {},
      "uniqueConstraints": {},
      "policies": {},
      "checkConstraints": {},
      "isRLSEnabled": false
    },
    "designers.moodboard_versions": {
      "name": "moodboard_versions",
      "schema": "designers",
      "columns": {
        "id": {
          "name": "id",
          "type": "uuid",
          "primaryKey": true,
          "notNull": true,
          "default": "gen_random_uuid()"
        },
        "moodboard_id": {
          "name": "moodboard_id",
          "type": "uuid",
          "primaryKey": false,
          "notNull": true
        },
        "name": {
          "name": "name",
          "type": "text",
          "primaryKey": false,
          "notNull": true,
          "default": "'Untitled version'"
        },
        "approval_status": {
          "name": "approval_status",
          "type": "text",
          "primaryKey": false,
          "notNull": true,
          "default": "'draft'"
        },
        "locked": {
          "name": "locked",
          "type": "boolean",
          "primaryKey": false,
          "notNull": false,
          "default": false
        },
        "major_version": {
          "name": "major_version",
          "type": "integer",
          "primaryKey": false,
          "notNull": true,
          "default": 1
        },
        "version_number": {
          "name": "version_number",
          "type": "integer",
          "primaryKey": false,
          "notNull": true,
          "default": 1
        },
        "snapshot": {
          "name": "snapshot",
          "type": "jsonb",
          "primaryKey": false,
          "notNull": true,
          "default": "'{}'::jsonb"
        },
        "created_at": {
          "name": "created_at",
          "type": "timestamp with time zone",
          "primaryKey": false,
          "notNull": true,
          "default": "now()"
        }
      },
      "indexes": {},
      "foreignKeys": {
        "moodboard_versions_moodboard_id_moodboards_id_fk": {
          "name": "moodboard_versions_moodboard_id_moodboards_id_fk",
          "tableFrom": "moodboard_versions",
          "tableTo": "moodboards",
          "schemaTo": "designers",
          "columnsFrom": [
            "moodboard_id"
          ],
          "columnsTo": [
            "id"
          ],
          "onDelete": "cascade",
          "onUpdate": "no action"
        }
      },
      "compositePrimaryKeys": {},
      "uniqueConstraints": {},
      "policies": {},
      "checkConstraints": {},
      "isRLSEnabled": false
    },
    "designers.moodboards": {
      "name": "moodboards",
      "schema": "designers",
      "columns": {
        "id": {
          "name": "id",
          "type": "uuid",
          "primaryKey": true,
          "notNull": true,
          "default": "gen_random_uuid()"
        },
        "created_by": {
          "name": "created_by",
          "type": "uuid",
          "primaryKey": false,
          "notNull": true
        },
        "team_id": {
          "name": "team_id",
          "type": "uuid",
          "primaryKey": false,
          "notNull": false
        },
        "project_id": {
          "name": "project_id",
          "type": "uuid",
          "primaryKey": false,
          "notNull": true
        },
        "room_id": {
          "name": "room_id",
          "type": "uuid",
          "primaryKey": false,
          "notNull": false
        },
        "shared_version_id": {
          "name": "shared_version_id",
          "type": "uuid",
          "primaryKey": false,
          "notNull": false
        },
        "name": {
          "name": "name",
          "type": "text",
          "primaryKey": false,
          "notNull": true,
          "default": "'Untitled Moodboard'"
        },
        "ai_image_url": {
          "name": "ai_image_url",
          "type": "text",
          "primaryKey": false,
          "notNull": false
        },
        "approval_status": {
          "name": "approval_status",
          "type": "text",
          "primaryKey": false,
          "notNull": false
        },
        "approval_note": {
          "name": "approval_note",
          "type": "text",
          "primaryKey": false,
          "notNull": false
        },
        "bg_color": {
          "name": "bg_color",
          "type": "text",
          "primaryKey": false,
          "notNull": false
        },
        "light_x": {
          "name": "light_x",
          "type": "double precision",
          "primaryKey": false,
          "notNull": false
        },
        "light_y": {
          "name": "light_y",
          "type": "double precision",
          "primaryKey": false,
          "notNull": false
        },
        "onboarding_complete": {
          "name": "onboarding_complete",
          "type": "boolean",
          "primaryKey": false,
          "notNull": true,
          "default": false
        },
        "share_settings": {
          "name": "share_settings",
          "type": "jsonb",
          "primaryKey": false,
          "notNull": false
        },
        "share_token": {
          "name": "share_token",
          "type": "text",
          "primaryKey": false,
          "notNull": false
        },
        "slide_bg_colors": {
          "name": "slide_bg_colors",
          "type": "jsonb",
          "primaryKey": false,
          "notNull": true,
          "default": "'{}'::jsonb"
        },
        "slide_hidden": {
          "name": "slide_hidden",
          "type": "jsonb",
          "primaryKey": false,
          "notNull": true,
          "default": "'{}'::jsonb"
        },
        "slide_names": {
          "name": "slide_names",
          "type": "jsonb",
          "primaryKey": false,
          "notNull": false
        },
        "slide_rooms": {
          "name": "slide_rooms",
          "type": "jsonb",
          "primaryKey": false,
          "notNull": true,
          "default": "'{}'::jsonb"
        },
        "tab_kind": {
          "name": "tab_kind",
          "type": "text",
          "primaryKey": false,
          "notNull": true,
          "default": "'main'"
        },
        "tab_label": {
          "name": "tab_label",
          "type": "text",
          "primaryKey": false,
          "notNull": false
        },
        "tab_order": {
          "name": "tab_order",
          "type": "integer",
          "primaryKey": false,
          "notNull": true,
          "default": 0
        },
        "created_at": {
          "name": "created_at",
          "type": "timestamp with time zone",
          "primaryKey": false,
          "notNull": true,
          "default": "now()"
        },
        "updated_at": {
          "name": "updated_at",
          "type": "timestamp with time zone",
          "primaryKey": false,
          "notNull": true,
          "default": "now()"
        }
      },
      "indexes": {},
      "foreignKeys": {},
      "compositePrimaryKeys": {},
      "uniqueConstraints": {
        "moodboards_share_token_unique": {
          "name": "moodboards_share_token_unique",
          "nullsNotDistinct": false,
          "columns": [
            "share_token"
          ]
        }
      },
      "policies": {},
      "checkConstraints": {},
      "isRLSEnabled": false
    }
  },
  "enums": {},
  "schemas": {
    "designers": "designers"
  },
  "sequences": {},
  "roles": {},
  "policies": {},
  "views": {},
  "_meta": {
    "columns": {},
    "schemas": {},
    "tables": {}
  }
}